maisaedu_utilities_prefect
