Metadata-Version: 2.1
Name: maisaedu-utilities-prefect
Version: 1.2.74
Summary: Utilities for interaction with Prefect, for +A Education
Home-page: UNKNOWN
Author: A+ Educação
Author-email: dataeng@maisaedu.com.br
License: MIT License
Platform: UNKNOWN
License-File: LICENSE
